autoreject/__init__.py
autoreject/__main__.py
autoreject/autoreject.py
mastodon_autoreject-0.0.2.dist-info/LICENSE
mastodon_autoreject-0.0.2.dist-info/METADATA
mastodon_autoreject-0.0.2.dist-info/WHEEL
mastodon_autoreject-0.0.2.dist-info/top_level.txt
mastodon_autoreject-0.0.2.dist-info/RECORD
