Metadata-Version: 2.1
Name: mastodon-autoreject
Version: 0.0.2
Summary: An automatic follow request rejector for Mastodon
Home-page: https://gitlab.com/mdszy/autoreject
Author: Mark
Author-email: mark@szy.io
License: UNKNOWN
Platform: UNKNOWN
Classifier: Programming Language :: Python :: 3
Classifier: Development Status :: 2 - Pre-Alpha
Classifier: License :: Public Domain
Classifier: Operating System :: OS Independent
Requires-Python: >=3.6
